nicegui_minesweeper/__init__.py
nicegui_minesweeper/minesweeper.py
nicegui_minesweeper/py.typed
nicegui_minesweeper-0.1.1.dist-info/METADATA
nicegui_minesweeper-0.1.1.dist-info/WHEEL
nicegui_minesweeper-0.1.1.dist-info/entry_points.txt
nicegui_minesweeper-0.1.1.dist-info/licenses/LICENSE
nicegui_minesweeper-0.1.1.dist-info/RECORD
